mountaintop/VERSION
mountaintop/__init__.py
mountaintop/configuration.py
mountaintop/bin/__init__.py
mountaintop/bin/average.py
mountaintop/bin/eval.py
mountaintop/bin/export.py
mountaintop/bin/main.py
mountaintop/bin/parser.py
mountaintop/bin/parser_base.py
mountaintop/bin/profiler.py
mountaintop/bin/train.py
mountaintop/bin/visual.py
mountaintop/bin/asr/__init__.py
mountaintop/bin/asr/decode.py
mountaintop/bin/asr/wer.py
mountaintop/core/__init__.py
mountaintop/core/beam_search.py
mountaintop/core/audio/__init__.py
mountaintop/core/audio/cmvn.py
mountaintop/core/audio/wer.py
mountaintop/core/internal/__init__.py
mountaintop/core/internal/container.py
mountaintop/core/internal/distribute.py
mountaintop/core/internal/module.py
mountaintop/core/internal/timing.py
mountaintop/core/internal/typing.py
mountaintop/core/ops/__init__.py
mountaintop/core/ops/common.py
mountaintop/core/ops/mask.py
mountaintop/dataset/__init__.py
mountaintop/dataset/base.py
mountaintop/dataset/sampler.py
mountaintop/dataset/asr/__init__.py
mountaintop/dataset/asr/fetcher.py
mountaintop/dataset/asr/loader.py
mountaintop/dataset/vad/__init__.py
mountaintop/dataset/vad/fetcher.py
mountaintop/dataset/vad/loader.py
mountaintop/layers/__init__.py
mountaintop/layers/activation.py
mountaintop/layers/loss.py
mountaintop/layers/normalization.py
mountaintop/layers/optimizer.py
mountaintop/layers/speech_embed.py
mountaintop/layers/subsampling.py
mountaintop/layers/base/__init__.py
mountaintop/layers/base/dataclass.py
mountaintop/layers/base/interface.py
mountaintop/layers/low_rank_transformer/__init__.py
mountaintop/layers/low_rank_transformer/low_rank_attention.py
mountaintop/layers/low_rank_transformer/low_rank_decoder.py
mountaintop/layers/low_rank_transformer/low_rank_decoder_block.py
mountaintop/layers/low_rank_transformer/low_rank_encoder.py
mountaintop/layers/low_rank_transformer/low_rank_encoder_block.py
mountaintop/layers/low_rank_transformer/low_rank_forward.py
mountaintop-0.1.3.dist-info/METADATA
mountaintop-0.1.3.dist-info/WHEEL
mountaintop-0.1.3.dist-info/entry_points.txt
mountaintop-0.1.3.dist-info/top_level.txt
mountaintop-0.1.3.dist-info/RECORD
